odds/GOP.py
odds/__init__.py
odds/ae.py
odds/dens_os.py
odds/gru.py
odds/odds.py
odds/outlier_pursuit.py
odds/reg_os.py
odds/utils.py
odds/vae.py
odds-0.2.2.dist-info/LICENSE
odds-0.2.2.dist-info/METADATA
odds-0.2.2.dist-info/WHEEL
odds-0.2.2.dist-info/top_level.txt
odds-0.2.2.dist-info/RECORD
